Metadata-Version: 1.1
Name: GCAP
Version: 1.1-20140805
Summary: DNase I seq QC pipeline
Home-page: https://github.com/qinqian/GCAP
Author: Qian Qin
Author-email: qianqind@gmail.com
License: GNU
Platform: UNKNOWN
Classifier: Development Status :: 4 - Beta
Classifier: Environment :: Console
Classifier: Intended Audience :: Developers
Classifier: Intended Audience :: End Users/Desktop
Classifier: License :: OSI Approved :: Python Software Foundation License
Classifier: Operating System :: MacOS :: MacOS X
Classifier: Operating System :: POSIX
Classifier: Programming Language :: Python :: 3
Classifier: Topic :: Software Development :: Libraries :: Python Modules
